czyRequest.py
setup.py
czyRequest.egg-info/PKG-INFO
czyRequest.egg-info/SOURCES.txt
czyRequest.egg-info/dependency_links.txt
czyRequest.egg-info/top_level.txt