Metadata-Version: 1.0
Name: czyRequest
Version: 1.0
Summary: requests优化
Home-page: https://www.cnblogs.com/RainBol/
Author: RainBol
Author-email: 2497643794@qq.com
License: UNKNOWN
Platform: UNKNOWN
